[
null,
{"id":1,"expanded":true,"name":"Ichimaru ramen","order":2,"parentId":2,"scrollX":647.6,"scrollY":366},
{"id":2,"expanded":true,"name":"Konoha SUR","order":1,"parentId":0,"scrollX":792.4,"scrollY":809.2},
{"id":3,"expanded":false,"name":"Floreria","order":3,"parentId":2,"scrollX":647.6,"scrollY":360},
{"id":4,"expanded":true,"name":"Hospital","order":4,"parentId":2,"scrollX":809.5,"scrollY":456.5},
{"id":5,"expanded":true,"name":"Cuartotest","order":5,"parentId":4,"scrollX":811,"scrollY":453.5},
{"id":6,"expanded":false,"name":"Cuarto2","order":6,"parentId":4,"scrollX":647.6,"scrollY":366.4},
{"id":7,"expanded":true,"name":"Casa Tsunade","order":7,"parentId":2,"scrollX":654,"scrollY":369.6},
{"id":8,"expanded":true,"name":"Lavadora","order":8,"parentId":7,"scrollX":647.6,"scrollY":366.4},
{"id":9,"expanded":true,"name":"Hall","order":10,"parentId":7,"scrollX":647.6,"scrollY":359.6},
{"id":10,"expanded":true,"name":"Cama tsunade","order":11,"parentId":9,"scrollX":588.7272727272727,"scrollY":333.09090909090907},
{"id":11,"expanded":false,"name":"Naruto tsunade","order":12,"parentId":9,"scrollX":647.6,"scrollY":360},
{"id":12,"expanded":true,"name":"Konoha NORTE","order":13,"parentId":0,"scrollX":760.4,"scrollY":359.6},
{"id":13,"expanded":true,"name":"Academia ninja","order":17,"parentId":12,"scrollX":647.6,"scrollY":502.8},
{"id":14,"expanded":false,"name":"Sala misiones","order":18,"parentId":13,"scrollX":647.6,"scrollY":366.4},
{"id":15,"expanded":false,"name":"SalonClases","order":19,"parentId":13,"scrollX":647.6,"scrollY":389.2},
{"id":16,"expanded":true,"name":"Oficina Tsunade","order":14,"parentId":12,"scrollX":647.6,"scrollY":366},
{"id":17,"expanded":true,"name":"MAP017","order":33,"parentId":0,"scrollX":647.6,"scrollY":366},
{"id":18,"expanded":true,"name":"Campo entrenamiento","order":15,"parentId":12,"scrollX":779.6,"scrollY":359.6},
{"id":19,"expanded":true,"name":"Konoha Road","order":21,"parentId":0,"scrollX":779.6,"scrollY":827.6},
{"id":20,"expanded":false,"name":"Casa Naruto","order":16,"parentId":12,"scrollX":647.6,"scrollY":366},
{"id":21,"expanded":false,"name":"1Left","order":23,"parentId":19,"scrollX":901.2,"scrollY":503.6},
{"id":22,"expanded":false,"name":"Antiguedades","order":20,"parentId":12,"scrollX":647.6,"scrollY":366},
{"id":23,"expanded":false,"name":"2D","order":24,"parentId":19,"scrollX":647.6,"scrollY":862},
{"id":24,"expanded":false,"name":"3D","order":25,"parentId":19,"scrollX":832.4,"scrollY":359.6},
{"id":25,"expanded":true,"name":"C","order":35,"parentId":17,"scrollX":810.8,"scrollY":449.2},
{"id":26,"expanded":true,"name":"Sand Road","order":26,"parentId":0,"scrollX":834.8,"scrollY":511.6},
{"id":27,"expanded":true,"name":"S2","order":27,"parentId":26,"scrollX":647.6,"scrollY":584.4},
{"id":28,"expanded":false,"name":"Main Room","order":31,"parentId":31,"scrollX":647.6,"scrollY":359.6},
{"id":29,"expanded":false,"name":"Gates","order":22,"parentId":19,"scrollX":647.6,"scrollY":450},
{"id":30,"expanded":false,"name":"Gates","order":28,"parentId":26,"scrollX":647.6,"scrollY":366},
{"id":31,"expanded":true,"name":"Sand village","order":29,"parentId":0,"scrollX":835.6,"scrollY":751.6},
{"id":32,"expanded":false,"name":"Hotel","order":30,"parentId":31,"scrollX":654,"scrollY":402},
{"id":33,"expanded":false,"name":"Hall","order":32,"parentId":31,"scrollX":654,"scrollY":402},
{"id":34,"expanded":false,"name":"GaleriaThis","order":9,"parentId":8,"scrollX":647.6,"scrollY":360},
{"id":35,"expanded":true,"name":"MAP035","order":34,"parentId":17,"scrollX":647.6,"scrollY":359.6},
{"id":36,"expanded":false,"name":"test1","order":36,"parentId":17,"scrollX":647.6,"scrollY":359.6},
{"id":37,"expanded":true,"name":"test2","order":37,"parentId":17,"scrollX":647.6,"scrollY":359.6},
{"id":38,"expanded":false,"name":"test3","order":38,"parentId":17,"scrollX":647.6,"scrollY":359.6,"quick":false},
{"id":39,"expanded":false,"name":"MAP039","order":39,"parentId":17,"scrollX":882,"scrollY":366,"quick":false}
]